Workbook

Sheet Premissas
A1: Zela Escola: premissas de preço
A2: Células em azul são entradas (edite aqui). Valores são estimativas de mercado, não pesquisa de concorrentes.
A3: Item | B3: R$ por aluno/mês (avulso) | C3: Essencial | D3: Completo | E3: Premium
A4: Plano base | B4: 6.9 | C4: 1 | D4: 1 | E4: 1
A5: Pedagógico | B5: 3.5 | C5: 0 | D5: 1 | E5: 1
A6: Rotina e família | B6: 2.5 | C6: 0 | D6: 1 | E6: 1
A7: Chat | B7: 1.5 | C7: 0 | D7: 0 | E7: 1
A8: Prova de vida | B8: 1.5 | C8: 0 | D8: 0 | E8: 1
A9: Entrada por QR Code | B9: 1 | C9: 0 | D9: 0 | E9: 1
A11: Soma dos avulsos por aluno | C11: =SUMPRODUCT($B$4:$B$9,C4:C9) | D11: =SUMPRODUCT($B$4:$B$9,D4:D9) | E11: =SUMPRODUCT($B$4:$B$9,E4:E9)
A12: Preço do pacote por aluno/mês (tabela) | C12: 6.9 | D12: 11.9 | E12: 15.9
A13: Desconto implícito do pacote | C13: =IF(C11=0,0,1-C12/C11) | D13: =IF(D11=0,0,1-D12/D11) | E13: =IF(E11=0,0,1-E12/E11)
A14: Mínimo mensal por escola | C14: 450 | D14: 790 | E14: 990
A15: Custo estimado por aluno/mês (hipótese) | C15: 1.5 | D15: 1.8 | E15: 2.2
A17: Implantação (valor único), mínimo | B17: 600
A18: Implantação (valor único), máximo | B18: 1200
A19: App com a marca da escola: setup | B19: R$ 2.500 a 4.000
A20: App com a marca da escola: mensal | B20: R$ 300 a 600
A22: Notas
A23: Custo por aluno é hipótese: validar com consumo real de Supabase, Storage e egress da biometria.
A24: Taxas do Asaas (boleto e Pix) são da escola. Hardware do totem é vendido à parte.
A25: NFS-e fica no plano base. Os apps Capacitor começam em 01/10/2026, com lançamento previsto para janeiro de 2027.

Sheet Simulação
A1: Simulação por tamanho de escola
A2: Mensalidade = maior valor entre alunos x preço e o mínimo mensal. Edite os tamanhos em azul.
A4: Alunos ativos | B4: Essencial (mês) | C4: Completo (mês) | D4: Premium (mês) | E4: Essencial (ano) | F4: Completo (ano) | G4: Premium (ano) | H4: Margem Essencial | I4: Margem Completo | J4: Margem Premium
A5: 30 | B5: =MAX($A5*Premissas!C$12,Premissas!C$14) | C5: =MAX($A5*Premissas!D$12,Premissas!D$14) | D5: =MAX($A5*Premissas!E$12,Premissas!E$14) | E5: =B5*12 | F5: =C5*12 | G5: =D5*12 | H5: =(B5-$A5*Premissas!C$15)/B5 | I5: =(C5-$A5*Premissas!D$15)/C5 | J5: =(D5-$A5*Premissas!E$15)/D5
A6: 60 | B6: =MAX($A6*Premissas!C$12,Premissas!C$14) | C6: =MAX($A6*Premissas!D$12,Premissas!D$14) | D6: =MAX($A6*Premissas!E$12,Premissas!E$14) | E6: =B6*12 | F6: =C6*12 | G6: =D6*12 | H6: =(B6-$A6*Premissas!C$15)/B6 | I6: =(C6-$A6*Premissas!D$15)/C6 | J6: =(D6-$A6*Premissas!E$15)/D6
A7: 100 | B7: =MAX($A7*Premissas!C$12,Premissas!C$14) | C7: =MAX($A7*Premissas!D$12,Premissas!D$14) | D7: =MAX($A7*Premissas!E$12,Premissas!E$14) | E7: =B7*12 | F7: =C7*12 | G7: =D7*12 | H7: =(B7-$A7*Premissas!C$15)/B7 | I7: =(C7-$A7*Premissas!D$15)/C7 | J7: =(D7-$A7*Premissas!E$15)/D7
A8: 120 | B8: =MAX($A8*Premissas!C$12,Premissas!C$14) | C8: =MAX($A8*Premissas!D$12,Premissas!D$14) | D8: =MAX($A8*Premissas!E$12,Premissas!E$14) | E8: =B8*12 | F8: =C8*12 | G8: =D8*12 | H8: =(B8-$A8*Premissas!C$15)/B8 | I8: =(C8-$A8*Premissas!D$15)/C8 | J8: =(D8-$A8*Premissas!E$15)/D8
A9: 200 | B9: =MAX($A9*Premissas!C$12,Premissas!C$14) | C9: =MAX($A9*Premissas!D$12,Premissas!D$14) | D9: =MAX($A9*Premissas!E$12,Premissas!E$14) | E9: =B9*12 | F9: =C9*12 | G9: =D9*12 | H9: =(B9-$A9*Premissas!C$15)/B9 | I9: =(C9-$A9*Premissas!D$15)/C9 | J9: =(D9-$A9*Premissas!E$15)/D9
A10: 300 | B10: =MAX($A10*Premissas!C$12,Premissas!C$14) | C10: =MAX($A10*Premissas!D$12,Premissas!D$14) | D10: =MAX($A10*Premissas!E$12,Premissas!E$14) | E10: =B10*12 | F10: =C10*12 | G10: =D10*12 | H10: =(B10-$A10*Premissas!C$15)/B10 | I10: =(C10-$A10*Premissas!D$15)/C10 | J10: =(D10-$A10*Premissas!E$15)/D10
A11: 500 | B11: =MAX($A11*Premissas!C$12,Premissas!C$14) | C11: =MAX($A11*Premissas!D$12,Premissas!D$14) | D11: =MAX($A11*Premissas!E$12,Premissas!E$14) | E11: =B11*12 | F11: =C11*12 | G11: =D11*12 | H11: =(B11-$A11*Premissas!C$15)/B11 | I11: =(C11-$A11*Premissas!D$15)/C11 | J11: =(D11-$A11*Premissas!E$15)/D11
A13: Margem considera só o custo variável por aluno das Premissas, sem equipe, impostos ou suporte.

Sheet Sob medida
A1: Escola sob medida (módulos avulsos)
A2: Preencha o que está em amarelo. Use 1 para contratar e 0 para não contratar. Exemplo já preenchido.
A4: Alunos ativos | B4: 120
A6: Item | B6: Contratar (1 ou 0) | C6: R$ por aluno
A7: Plano base | B7: 1 | C7: =Premissas!B4
A8: Pedagógico | B8: 1 | C8: =Premissas!B5
A9: Rotina e família | B9: 0 | C9: =Premissas!B6
A10: Chat | B10: 1 | C10: =Premissas!B7
A11: Prova de vida | B11: 0 | C11: =Premissas!B8
A12: Entrada por QR Code | B12: 1 | C12: =Premissas!B9
A14: Valor por aluno/mês | B14: =SUMPRODUCT(B7:B12,C7:C12)
A15: Mensalidade avulsa | B15: =MAX(B4*B14,Premissas!C14)
A16: Dica | B16: =IF(B15>=B18,"Avulso passou do Completo: vale oferecer o pacote","Avulso está abaixo do Completo")
A17: Mensalidade Premium (referência) | B17: =MAX(B4*Premissas!E12,Premissas!E14)
A18: Mensalidade Completo (referência) | B18: =MAX(B4*Premissas!D12,Premissas!D14)
